{"api_endpoints.md":"DFTC8Rf4","api_reference.md":"B7oNh2f4","guide_advanced.md":"C5O0lo_-","guide_authentication.md":"Jstv2QAf","guide_big-data.md":"Cvb6q_KT","guide_coding-standards.md":"Cmx4Qrwh","guide_configuration.md":"_W6eAvI-","guide_custom-code.md":"MeLmj2SE","guide_database.md":"CLjgF_1k","guide_debugging.md":"BfkeV1Mw","guide_modern-features.md":"BBbdTaCX","guide_performance-optimization.md":"pdvBqHBU","guide_plugin-system.md":"t2fauHF_","guide_quick-start.md":"D67HvMFj","guide_request-response.md":"BFOLtbMt","guide_routing.md":"Bdh4dUcR","guide_security.md":"BlD2C-ef","guide_testing.md":"DXnaOVSD","guide_token-strategy.md":"DL7LQmym","guide_tools.md":"Wz4a4leA","index.md":"BGew8acE"}
